dexml/__init__.py
dexml/__main__.py
dexml/cli/__init__.py
dexml/cli/cli.py
dexml/cli/generator.py
dexml/constants.py
dexml/exceptions.py
dexml/fields/__init__.py
dexml/fields/choice.py
dexml/fields/dict.py
dexml/fields/field.py
dexml/fields/list.py
dexml/fields/model.py
dexml/fields/values.py
dexml/fields/xmlnode.py
dexml/meta.py
dexml/model.py
dexml_python3-0.1.8.dist-info/WHEEL
dexml_python3-0.1.8.dist-info/METADATA
dexml_python3-0.1.8.dist-info/RECORD
