Metadata-Version: 2.1
Name: dexml-python3
Version: 0.1.8
Summary: A dead-simple xml object mapper for Python
Home-page: https://github.com/pwithams/dexml-python3
Author: Patrick Withams
Author-email: pwithams@gmail.com
Requires-Python: >=3.7.2,<4.0.0
Classifier: Programming Language :: Python :: 3
Classifier: Programming Language :: Python :: 3.8
Classifier: Programming Language :: Python :: 3.9
Classifier: Programming Language :: Python :: 3.10
Classifier: Programming Language :: Python :: 3.11
Requires-Dist: typer[all] (>=0.7.0,<0.8.0)
Requires-Dist: xmltodict (>=0.13.0,<0.14.0)
Project-URL: Repository, https://github.com/pwithams/dexml-python3
